andyutil/__init__.py
andyutil/util.py
andyutil/data/domains.txt
andyutil/string/__init__.py
andyutil/string/string_util.py
calc/__init__.py
calc/util.py
calc/string/__init__.py
calc/string/string_util.py
andytestutil-1.2.dist-info/METADATA
andytestutil-1.2.dist-info/WHEEL
andytestutil-1.2.dist-info/top_level.txt
andytestutil-1.2.dist-info/RECORD
